snakemake_interface_report_plugins/__init__.py
snakemake_interface_report_plugins/common.py
snakemake_interface_report_plugins/interfaces.py
snakemake_interface_report_plugins/registry/__init__.py
snakemake_interface_report_plugins/registry/plugin.py
snakemake_interface_report_plugins/reporter.py
snakemake_interface_report_plugins/settings.py
snakemake_interface_report_plugins-1.2.0.dist-info/LICENSE
snakemake_interface_report_plugins-1.2.0.dist-info/METADATA
snakemake_interface_report_plugins-1.2.0.dist-info/WHEEL
snakemake_interface_report_plugins-1.2.0.dist-info/RECORD
