Metadata-Version: 2.3
Name: snakemake-interface-report-plugins
Version: 1.2.0
Summary: The interface for Snakemake report plugins.
Author: Johannes Koester
Author-email: johannes.koester@uni-due.de
Requires-Python: >=3.11,<4.0
Classifier: Programming Language :: Python :: 3
Classifier: Programming Language :: Python :: 3.11
Classifier: Programming Language :: Python :: 3.12
Classifier: Programming Language :: Python :: 3.13
Requires-Dist: snakemake-interface-common (>=1.16.0,<2.0.0)
